README.md
setup.cfg
setup.py
gaesessions/__init__.py
gaesessions.egg-info/PKG-INFO
gaesessions.egg-info/SOURCES.txt
gaesessions.egg-info/dependency_links.txt
gaesessions.egg-info/top_level.txt