Metadata-Version: 1.0
Name: gaesessions
Version: 1.0.7
Summary: gae-sessions is a sessions library for the Python runtime on Google App Engine for ALL session sizes. It is extremely fast, lightweight (one file), and easy to use. This is a packed version of the inactive project at https://github.com/dound/gae-sessions
Home-page: https://github.com/lagren/gae-sessions
Author: Eirik Tenold
Author-email: eirik@relativt.net
License: Apache License Version 2.0
Platform: UNKNOWN
